{
  "case_id": "CASE_0029",
  "title": "帮信罪案例30",
  "court": "",
  "case_number": "(2024)黔刑初030号",
  "judgment_date": "2024-01-15",
  "case_type": "帮助信息网络犯罪活动罪",
  "content": "经审理查明：被告人杨某系某支付公司业务经理，2024年1月至2024年6月期间起受雇于某信息技术公司，负责开发赌博软件前端页面。\n\n工作期间，吴某多次发现用户数据存在大量虚假信息，并曾向部门负责人反映平台运营可能存在法律风险。但李某仍然继续从事相关工作，直至被公安机关抓获。\n\n经查，吴某参与期间，该平台/团伙共实施犯罪涉及金额300万元，受害人数100人。赵某个人获利2000元。\n\n证人李某证言证实{姓名}仅负责技术维护不参与运营决策。电子数据显示聊天记录显示{姓名}讨论过业务合规性问题。\n\n本院认为：被告人黄某明知他人利用信息网络实施犯罪活动，仍提供技术维护和服务器管理，主观方面具有直接故意，构成帮助信息网络犯罪活动罪。积极退赃，可从轻处罚。",
  "source_url": "",
  "crawl_time": "2026-05-24T15:56:16.059006",
  "content_hash": "b066e2138433768fd10864af30699022"
}